sqliteimport/__init__.py
sqliteimport/__main__.py
sqliteimport/accessor.py
sqliteimport/bundler.py
sqliteimport/cli.py
sqliteimport/compat.py
sqliteimport/compiler.py
sqliteimport/errors.py
sqliteimport/importer.py
sqliteimport/injector-template.py
sqliteimport/injector.py
sqliteimport/py.typed
sqliteimport/util.py
sqliteimport-0.14.0.dist-info/METADATA
sqliteimport-0.14.0.dist-info/WHEEL
sqliteimport-0.14.0.dist-info/entry_points.txt
sqliteimport-0.14.0.dist-info/licenses/LICENSE.txt
sqliteimport-0.14.0.dist-info/RECORD
