Metadata-Version: 2.4
Name: sqliteimport
Version: 0.14.0
Summary: Import Python code from sqlite databases
License-Expression: MIT
License-File: LICENSE.txt
Keywords: sqlite,import,importlib
Author: Kurt McKee
Author-email: contactme@kurtmckee.org
Requires-Python: >=3.10
Classifier: Development Status :: 3 - Alpha
Classifier: Intended Audience :: Developers
Classifier: License :: OSI Approved :: MIT License
Classifier: Programming Language :: Python :: 3
Classifier: Topic :: Software Development :: Libraries :: Python Modules
Provides-Extra: cli
Requires-Dist: click (>=8,<9) ; extra == "cli"
Requires-Dist: prettytable (>=3.15.1,<4) ; extra == "cli"
Project-URL: Changelog, https://sqliteimport.readthedocs.io/en/latest/changelog/
Project-URL: Documentation, https://sqliteimport.readthedocs.io/en/latest/
Project-URL: Donate via GitHub, https://github.com/sponsors/kurtmckee
Project-URL: Donate via Ko-Fi, https://ko-fi.com/kurtmckee
Project-URL: Source, https://github.com/kurtmckee/sqliteimport
